bc125py/__init__.py
bc125py/__main__.py
bc125py/con.py
bc125py/mappings.py
bc125py/sdo.py
bc125py/app/__init__.py
bc125py/app/cli.py
bc125py/app/core.py
bc125py/app/log.py
bc125py-1.0.0.dist-info/LICENSE
bc125py-1.0.0.dist-info/METADATA
bc125py-1.0.0.dist-info/WHEEL
bc125py-1.0.0.dist-info/entry_points.txt
bc125py-1.0.0.dist-info/top_level.txt
bc125py-1.0.0.dist-info/RECORD
