Metadata-Version: 2.1
Name: bc125py
Version: 1.0.0
Summary: A Python-based interface for the Uniden BC125AT
Home-page: https://github.com/itsmaxymoo/bc125py
Author: Max Loiacono
Author-email: max.loiacono@protonmail.com
License: MIT License
Project-URL: Bug Tracker, https://github.com/itsmaxymoo/bc125py/issues
Classifier: Programming Language :: Python :: 3
Classifier: Topic :: Communications :: Ham Radio
Classifier: License :: OSI Approved :: MIT License
Classifier: Operating System :: POSIX :: Linux
Requires-Python: >=3.7
License-File: LICENSE
Requires-Dist: pyserial <4.0,>=3.0
